ARYAN/ARYAN1.py
ARYAN/ARYAN2.py
ARYAN/__init__.py
ARYAN_KADIYAN-0.0.1.dist-info/LICENCE
ARYAN_KADIYAN-0.0.1.dist-info/METADATA
ARYAN_KADIYAN-0.0.1.dist-info/WHEEL
ARYAN_KADIYAN-0.0.1.dist-info/top_level.txt
ARYAN_KADIYAN-0.0.1.dist-info/RECORD
